{"is_source_file": true, "format": "JavaScript", "description": "This file sets up testing configurations for a React application by importing custom jest matchers for DOM assertions.", "external_files": ["@testing-library/jest-dom"], "external_methods": [], "published": [], "classes": [], "methods": [], "calls": ["import '@testing-library/jest-dom'"], "search-terms": ["setupTests.js", "jest-dom", "testing-library", "React", "test setup"], "state": 2, "file_id": 5, "knowledge_revision": 24, "git_revision": "d5ed4311952b127d1b24bcab599443a7c28efee9", "ctags": [], "hash": "1a77571e1a8cf36018a41bcedf60db75", "format-version": 4, "code-base-name": "todo_frontend", "filename": "todo_frontend/src/setupTests.js", "revision_history": [{"24": "d5ed4311952b127d1b24bcab599443a7c28efee9"}]}